ydcv.py
ydcv-0.7.dist-info/LICENSE
ydcv-0.7.dist-info/METADATA
ydcv-0.7.dist-info/WHEEL
ydcv-0.7.dist-info/entry_points.txt
ydcv-0.7.dist-info/top_level.txt
ydcv-0.7.dist-info/RECORD
